{
  "id": "4087be12-2927-44ab-8452-ea54593ff9ab",
  "prevId": "fa944a32-0b88-4855-bd2e-3e91a8bf517d",
  "version": "7",
  "dialect": "postgresql",
  "tables": {
    "public.holidays": {
      "name": "holidays",
      "schema": "",
      "columns": {
        "id": {
          "name": "id",
          "type": "serial",
          "primaryKey": true,
          "notNull": true
        },
        "member_id": {
          "name": "member_id",
          "type": "integer",
          "primaryKey": false,
          "notNull": true
        },
        "start_date": {
          "name": "start_date",
          "type": "date",
          "primaryKey": false,
          "notNull": true
        },
        "end_date": {
          "name": "end_date",
          "type": "date",
          "primaryKey": false,
          "notNull": true
        },
        "description": {
          "name": "description",
          "type": "text",
          "primaryKey": false,
          "notNull": false
        },
        "created_at": {
          "name": "created_at",
          "type": "timestamp",
          "primaryKey": false,
          "notNull": true,
          "default": "now()"
        }
      },
      "indexes": {},
      "foreignKeys": {
        "holidays_member_id_team_members_id_fk": {
          "name": "holidays_member_id_team_members_id_fk",
          "tableFrom": "holidays",
          "tableTo": "team_members",
          "columnsFrom": [
            "member_id"
          ],
          "columnsTo": [
            "id"
          ],
          "onDelete": "no action",
          "onUpdate": "no action"
        }
      },
      "compositePrimaryKeys": {},
      "uniqueConstraints": {},
      "policies": {},
      "checkConstraints": {},
      "isRLSEnabled": false
    },
    "public.rota_assignments": {
      "name": "rota_assignments",
      "schema": "",
      "columns": {
        "id": {
          "name": "id",
          "type": "serial",
          "primaryKey": true,
          "notNull": true
        },
        "start_date": {
          "name": "start_date",
          "type": "date",
          "primaryKey": false,
          "notNull": true
        },
        "end_date": {
          "name": "end_date",
          "type": "date",
          "primaryKey": false,
          "notNull": true
        },
        "us_member_id": {
          "name": "us_member_id",
          "type": "integer",
          "primaryKey": false,
          "notNull": false
        },
        "uk_member_id": {
          "name": "uk_member_id",
          "type": "integer",
          "primaryKey": false,
          "notNull": false
        },
        "notes": {
          "name": "notes",
          "type": "text",
          "primaryKey": false,
          "notNull": false
        },
        "is_manual": {
          "name": "is_manual",
          "type": "boolean",
          "primaryKey": false,
          "notNull": true,
          "default": false
        },
        "created_at": {
          "name": "created_at",
          "type": "timestamp",
          "primaryKey": false,
          "notNull": true,
          "default": "now()"
        }
      },
      "indexes": {},
      "foreignKeys": {
        "rota_assignments_us_member_id_team_members_id_fk": {
          "name": "rota_assignments_us_member_id_team_members_id_fk",
          "tableFrom": "rota_assignments",
          "tableTo": "team_members",
          "columnsFrom": [
            "us_member_id"
          ],
          "columnsTo": [
            "id"
          ],
          "onDelete": "no action",
          "onUpdate": "no action"
        },
        "rota_assignments_uk_member_id_team_members_id_fk": {
          "name": "rota_assignments_uk_member_id_team_members_id_fk",
          "tableFrom": "rota_assignments",
          "tableTo": "team_members",
          "columnsFrom": [
            "uk_member_id"
          ],
          "columnsTo": [
            "id"
          ],
          "onDelete": "no action",
          "onUpdate": "no action"
        }
      },
      "compositePrimaryKeys": {},
      "uniqueConstraints": {},
      "policies": {},
      "checkConstraints": {},
      "isRLSEnabled": false
    },
    "public.rota_history": {
      "name": "rota_history",
      "schema": "",
      "columns": {
        "id": {
          "name": "id",
          "type": "serial",
          "primaryKey": true,
          "notNull": true
        },
        "member_id": {
          "name": "member_id",
          "type": "integer",
          "primaryKey": false,
          "notNull": true
        },
        "assignment_id": {
          "name": "assignment_id",
          "type": "integer",
          "primaryKey": false,
          "notNull": true
        },
        "region": {
          "name": "region",
          "type": "text",
          "primaryKey": false,
          "notNull": true
        },
        "start_date": {
          "name": "start_date",
          "type": "date",
          "primaryKey": false,
          "notNull": true
        },
        "end_date": {
          "name": "end_date",
          "type": "date",
          "primaryKey": false,
          "notNull": true
        }
      },
      "indexes": {},
      "foreignKeys": {
        "rota_history_member_id_team_members_id_fk": {
          "name": "rota_history_member_id_team_members_id_fk",
          "tableFrom": "rota_history",
          "tableTo": "team_members",
          "columnsFrom": [
            "member_id"
          ],
          "columnsTo": [
            "id"
          ],
          "onDelete": "no action",
          "onUpdate": "no action"
        },
        "rota_history_assignment_id_rota_assignments_id_fk": {
          "name": "rota_history_assignment_id_rota_assignments_id_fk",
          "tableFrom": "rota_history",
          "tableTo": "rota_assignments",
          "columnsFrom": [
            "assignment_id"
          ],
          "columnsTo": [
            "id"
          ],
          "onDelete": "no action",
          "onUpdate": "no action"
        }
      },
      "compositePrimaryKeys": {},
      "uniqueConstraints": {},
      "policies": {},
      "checkConstraints": {},
      "isRLSEnabled": false
    },
    "public.team_members": {
      "name": "team_members",
      "schema": "",
      "columns": {
        "id": {
          "name": "id",
          "type": "serial",
          "primaryKey": true,
          "notNull": true
        },
        "name": {
          "name": "name",
          "type": "text",
          "primaryKey": false,
          "notNull": true
        },
        "email": {
          "name": "email",
          "type": "text",
          "primaryKey": false,
          "notNull": true
        },
        "region": {
          "name": "region",
          "type": "text",
          "primaryKey": false,
          "notNull": true
        },
        "role": {
          "name": "role",
          "type": "text",
          "primaryKey": false,
          "notNull": true,
          "default": "'developer'"
        },
        "is_available": {
          "name": "is_available",
          "type": "boolean",
          "primaryKey": false,
          "notNull": true,
          "default": true
        },
        "holiday_start": {
          "name": "holiday_start",
          "type": "date",
          "primaryKey": false,
          "notNull": false
        },
        "holiday_end": {
          "name": "holiday_end",
          "type": "date",
          "primaryKey": false,
          "notNull": false
        }
      },
      "indexes": {},
      "foreignKeys": {},
      "compositePrimaryKeys": {},
      "uniqueConstraints": {
        "team_members_email_unique": {
          "name": "team_members_email_unique",
          "nullsNotDistinct": false,
          "columns": [
            "email"
          ]
        }
      },
      "policies": {},
      "checkConstraints": {},
      "isRLSEnabled": false
    }
  },
  "enums": {},
  "schemas": {},
  "sequences": {},
  "roles": {},
  "policies": {},
  "views": {},
  "_meta": {
    "columns": {},
    "schemas": {},
    "tables": {}
  }
}